{
  "Armor": 1,
  "Banner": 2,
  "Brewing ingredient": 3,
  "Bucket": 4,
  "Decoration": 5,
  "Dye": 6,
  "Dyed": 7,
  "End": 8,
  "Firework": 9,
  "Food": 10,
  "Liquid": 11,
  "Manufactured": 12,
  "Mechanism": 13,
  "Mob head": 14,
  "Natural": 15,
  "Nether": 16,
  "Non-solid": 17,
  "Ore": 18,
  "Plant": 19,
  "Smithing Template": 41,
  "Pottery Sherd": 44,
  "Bedrock Edition & Education Edition": 20,
  "Chemistry Miscellaneous": 33,
  "Element": 34,
  "Beaker": 35,
  "Flask": 36,
  "Jar": 37,
  "Potion": 21,
  "Splash potion": 22,
  "Lingering potion": 31,
  "Raw material": 23,
  "Spawn egg": 24,
  "Tool": 25,
  "Trimmed Armor": 43,
  "Utility": 26,
  "Vehicle": 27,
  "Weapon": 28,
  "Legacy: Potion": 45,
  "Legacy: Lingering Potion": 46,
  "Legacy: Splash Potion": 47,
  "Legacy: Spawn Eggs": 39,
  "Legacy: Dyed": 40,
  "Legacy: before 15w31a stair flip": 42,
  "Legacy: Miscellaneous": 29,
  "April Fools": 32,
  "Other": 30,
  "Minecraft Earth": 38
}